acquirest/__init__.py
acquirest/acquirest.py
acquirest-0.1.0.dist-info/AUTHORS.rst
acquirest-0.1.0.dist-info/LICENSE
acquirest-0.1.0.dist-info/METADATA
acquirest-0.1.0.dist-info/WHEEL
acquirest-0.1.0.dist-info/top_level.txt
acquirest-0.1.0.dist-info/RECORD
