Metadata-Version: 2.1
Name: acquirest
Version: 0.1.0
Summary: AcquiRest is a web service that turns PostgreSQL database into RESTful API.
Home-page: https://github.com/riiy/acquirest
Author: riiy
Author-email: zhangriiy@gmail.com
License: MIT license
Keywords: acquirest
Platform: UNKNOWN
Classifier: Development Status :: 2 - Pre-Alpha
Classifier: Intended Audience :: Developers
Classifier: License :: OSI Approved :: MIT License
Classifier: Natural Language :: English
Classifier: Programming Language :: Python :: 3
Classifier: Programming Language :: Python :: 3.6
Classifier: Programming Language :: Python :: 3.7
Classifier: Programming Language :: Python :: 3.8
Requires-Python: >=3.6
